<?xml version="1.0" encoding="UTF-8"?>
<odoo>

	<data>
		<record id="view_hr_overtime_request_mass_form"
			model="ir.ui.view">
			<field name="name">hr.overtime.request.mass.form</field>
			<field name="model">hr.overtime.request.mass</field>
			<field name="inherit_id"
				ref="viin_hr_overtime.view_hr_overtime_request_mass_form" />
			<field name="arch" type="xml">
				<xpath expr="//field[@name='mode']" position="after">
					<field name="approval_required" />
					<field name="approval_id" invisible="1" />
				</xpath>
			</field>
		</record>

	</data>
</odoo>